svmodule/__init__.py
svmodule/cli.py
svmodule/moddict.py
svmodule/parser.py
svmodule/printer.py
svmodule/test.py
svmodule/printers/__init__.py
svmodule/printers/align.py
svmodule/printers/clockingblock.py
svmodule/printers/doctable.py
svmodule/printers/importlist.py
svmodule/printers/initlatch.py
svmodule/printers/initwire.py
svmodule/printers/instance.py
svmodule/printers/logic.py
svmodule/printers/module.py
svmodule/printers/modulename.py
svmodule/printers/pandaxml.py
svmodule/printers/parameters.py
svmodule/printers/port_range.py
svmodule/printers/printerbase.py
svmodule/printers/signals.py
svmodule/printers/wavedisp.py
svmodule/printers/yaml.py
svmodule-1.2.0.dist-info/LICENSE
svmodule-1.2.0.dist-info/METADATA
svmodule-1.2.0.dist-info/WHEEL
svmodule-1.2.0.dist-info/entry_points.txt
svmodule-1.2.0.dist-info/top_level.txt
svmodule-1.2.0.dist-info/RECORD
