Metadata-Version: 2.1
Name: svmodule
Version: 1.2.0
Summary: [System]Verilog Module I/O parser and printer
Home-page: https://github.com/cclienti/svmodule
Author: Christophe Clienti
Author-email: cclienti@wavecruncher.net
License: GPL-3.0
Platform: UNKNOWN
Classifier: Programming Language :: Python :: 3
Classifier: License :: OSI Approved :: GNU General Public License v3 (GPLv3)
Classifier: Operating System :: OS Independent
Classifier: Development Status :: 5 - Production/Stable
Classifier: Environment :: Console
Classifier: Intended Audience :: Developers
